setup.py
bin/purge_key
bin/purge_service
bin/purge_url
ssfastly/__init__.py
ssfastly/auth.py
ssfastly/connection.py
ssfastly/errors.py
ssfastly/fastly.py
ssfastly/models.py
ssfastly.egg-info/PKG-INFO
ssfastly.egg-info/SOURCES.txt
ssfastly.egg-info/dependency_links.txt
ssfastly.egg-info/top_level.txt