Metadata-Version: 1.1
Name: ssfastly
Version: 0.0.4
Summary: SomeSpider Fastly python API fork
Home-page: https://github.com/somespider/fastly-py
Author: Edwin Fuquen
Author-email: tech@somespider.com
License: UNKNOWN
Keywords: fastly api somespider
Platform: UNKNOWN
Classifier: Operating System :: OS Independent
Classifier: Programming Language :: Python
Classifier: License :: OSI Approved :: MIT License
Classifier: Development Status :: 3 - Alpha
Classifier: Topic :: Utilities
